app/__init__.py
app/api/__init__.py
app/api/alert.py
app/api/auth.py
app/api/basic_auth_user.py
app/api/channel.py
app/api/event.py
app/api/healthy.py
app/api/integration.py
app/api/k8s.py
app/api/management.py
app/api/report.py
app/api/silence.py
app/api/user_notification_settings.py
app/auth/__init__.py
app/auth/basic_auth.py
app/auth/oauth2_keycloak.py
app/client/__init__.py
app/client/email_client.py
app/client/google_chat_client.py
app/client/httpx_client.py
app/client/kakaotalk_client.py
app/client/msteams_client.py
app/client/slack_client.py
app/client/webhook_client.py
app/db/__init__.py
app/db/activity_repository.py
app/db/alert_repository.py
app/db/base_repository.py
app/db/basic_auth_user_repository.py
app/db/channel_repository.py
app/db/exceptions.py
app/db/integration_repository.py
app/db/kakao_token_repository.py
app/db/search_utils.py
app/db/silence_repository.py
app/db/user_notification_settings_repository.py
app/event/__init__.py
app/event/event_handler.py
app/exception/__init__.py
app/exception/common_exception.py
app/k8s/__init__.py
app/k8s/kubernetes_proxy.py
app/main.py
app/model/__init__.py
app/model/alert_model.py
app/model/auth_model.py
app/model/channel_model.py
app/model/integration_model.py
app/model/kakaotalk_model.py
app/model/result_model.py
app/model/silence_model.py
app/model/user_notification_settings.py
app/scheduler/__init__.py
app/scheduler/wakeup_alert.py
app/schema/__init__.py
app/schema/alert_request_model.py
app/schema/basicauth_request_model.py
app/schema/channel_request_model.py
app/schema/integration_request_model.py
app/schema/list_model.py
app/schema/response_model.py
app/schema/silence_request_model.py
app/schema/user_notification_settings_request_model.py
app/service/__init__.py
app/service/alert_service.py
app/service/report_service.py
app/settings.py
app/thread/__init__.py
app/thread/threadpool_executor.py
app/utils/__init__.py
app/utils/encryption_utils.py
app/utils/list_utils.py
app/utils/time_utils.py
zcp_alert_backend-1.1.0.dist-info/LICENSE
zcp_alert_backend-1.1.0.dist-info/METADATA
zcp_alert_backend-1.1.0.dist-info/WHEEL
zcp_alert_backend-1.1.0.dist-info/RECORD
