Metadata-Version: 2.1
Name: zcp-alert-backend
Version: 1.1.0
Summary: This is the backend service for the alert management of the Cloud Z MP solution
License: Apache License Version 2.0
Author: Kilsoo Kang
Author-email: kilsoo75@gmail.com
Requires-Python: >=3.12,<4.0
Classifier: License :: Other/Proprietary License
Classifier: Programming Language :: Python :: 3
Classifier: Programming Language :: Python :: 3.12
Classifier: Programming Language :: Python :: 3.13
Requires-Dist: colorlog (==6.8.2)
Requires-Dist: cryptography (==43.0.0)
Requires-Dist: fastapi (==0.110)
Requires-Dist: httpx (==0.28.0)
Requires-Dist: jinja2 (==3.1.4)
Requires-Dist: kubernetes (==29.0.0)
Requires-Dist: pandas (==2.2.3)
Requires-Dist: pydantic (==2.8.2)
Requires-Dist: pyjwt (==2.9.0)
Requires-Dist: pymongo (==4.7.2)
Requires-Dist: python-dotenv (==1.0.1)
Requires-Dist: schedule (==1.2.2)
Requires-Dist: starlette-csrf (==3.0.0)
Requires-Dist: uvicorn (==0.30.5)
